<Properties StartupConfiguration="{64644A48-EB34-F8AD-8835-C46A8686EDC2}|">
  <MonoDevelop.Ide.Workspace ActiveConfiguration="Debug" />
  <MonoDevelop.Ide.DebuggingService.Breakpoints>
    <BreakpointStore />
  </MonoDevelop.Ide.DebuggingService.Breakpoints>
  <MonoDevelop.Ide.Workbench ActiveDocument="Assets/Scripts/BallMovement.cs">
    <Files>
      <File FileName="Assets/Scripts/BallMovement.cs" Line="64" Column="1" />
      <File FileName="Assets/Scripts/Movement.cs" />
    </Files>
    <Pads>
      <Pad Id="ProjectPad">
        <State name="__root__">
          <Node name="BreakoutClone" expanded="True">
            <Node name="Assets" expanded="True">
              <Node name="Scripts" expanded="True">
                <Node name="BallMovement.cs" selected="True" />
              </Node>
            </Node>
          </Node>
        </State>
      </Pad>
    </Pads>
  </MonoDevelop.Ide.Workbench>
  <MonoDevelop.Ide.DebuggingService.PinnedWatches />
  <MonoDevelop.Ide.ItemProperties.Assembly-CSharp PreferredExecutionTarget="b0aa8ef8-1a8d-4be5-83c5-2d2ccd5022e4" />
  <MultiItemStartupConfigurations />
</Properties>